<?xml version="1.0" encoding="windows-1251" ?>
<root>
    <branch alfa="0" texture="j:/Steel/Neko/SpeedTreeLib/Broadleaves/london plane/LondonPlaneBark.tga">
        <vertexs num="329">
            <point x="4.201158" y="-1.036675" z="0.000000" nx="0.139253" ny="-0.032751" nz="0.989715" s="0.000000" t="0.000000" p="0.000000" q="0.000000" />
            <point x="1.674713" y="0.681345" z="-0.001679" nx="-0.700461" ny="-0.706396" nz="0.096299" s="0.300000" t="0.000000" p="0.000000" q="0.000000" />
            <point x="1.203085" y="1.935743" z="-0.003425" nx="-0.782820" ny="-0.462131" nz="0.369147" s="0.600000" t="0.000000" p="0.000000" q="0.000000" />
            <point x="-0.289850" y="4.005705" z="-0.006036" nx="0.165780" ny="-0.707225" nz="0.678579" s="0.900000" t="0.000000" p="0.000000" q="0.000000" />
            <point x="-1.165514" y="1.382198" z="-0.001679" nx="0.914093" ny="-0.374751" nz="0.130991" s="1.200000" t="0.000000" p="0.000000" q="0.000000" />
            <point x="-1.755357" y="0.433151" z="0.000000" nx="-0.763909" ny="0.643291" nz="0.045776" s="1.500000" t="0.000000" p="0.000000" q="0.000000" />
            <point x="-3.543005" y="-1.441448" z="0.003553" nx="-0.699419" ny="-0.283649" nz="0.656014" s="1.800000" t="0.000000" p="0.000000" q="0.000000" />
            <point x="-0.954385" y="-1.535591" z="0.002717" nx="-0.628622" ny="-0.777426" nz="0.020861" s="2.100000" t="0.000000" p="0.000000" q="0.000000" />
            <point x="0.330961" y="-4.573824" z="0.006892" nx="0.059332" ny="-0.816078" nz="0.574887" s="2.400000" t="0.000000" p="0.000000" q="0.000000" />
            <point x="1.165515" y="-1.382197" z="0.001679" nx="0.674414" ny="-0.737864" nz="0.026686" s="2.700000" t="0.000000" p="0.000000" q="0.000000" />
            <point x="4.201164" y="-1.036672" z="-0.000000" nx="0.139252" ny="-0.032751" nz="0.989715" s="3.000000" t="0.000000" p="0.000000" q="0.000000" />
            <point x="4.176623" y="-1.030615" z="0.003653" nx="0.205870" ny="-0.041307" nz="0.977707" s="-0.000100" t="0.000452" p="0.000000" q="0.000000" />
            <point x="1.674398" y="0.681186" z="-0.005137" nx="0.703899" ny="0.707715" nz="0.054400" s="0.299900" t="0.000452" p="0.000000" q="0.000000" />
            <point x="1.200253" y="1.931152" z="-0.015177" nx="0.563389" ny="0.339840" nz="0.667582" s="0.599900" t="0.000452" p="0.000000" q="0.000000" />
            <point x="-0.288289" y="3.983308" z="-0.029760" nx="-0.036044" ny="0.175244" nz="0.971902" s="0.899900" t="0.000452" p="0.000000" q="0.000000" />
            <point x="-1.165316" y="1.381914" z="-0.003874" nx="-0.922196" ny="0.381563" nz="0.055601" s="1.199900" t="0.000452" p="0.000000" q="0.000000" />
            <point x="-1.755038" y="0.433082" z="0.006290" nx="-0.765240" ny="0.641505" nz="0.047694" s="1.499900" t="0.000452" p="0.000000" q="0.000000" />
            <point x="-3.523424" y="-1.433393" z="0.027913" nx="-0.308219" ny="-0.117892" nz="0.943982" s="1.799900" t="0.000452" p="0.000000" q="0.000000" />
            <point x="-0.954187" y="-1.535234" z="0.021955" nx="-0.627632" ny="-0.776348" nz="0.057689" s="2.099900" t="0.000452" p="0.000000" q="0.000000" />
            <point x="0.329063" y="-4.546576" z="0.045766" nx="0.023398" ny="-0.279211" nz="0.959945" s="2.399900" t="0.000452" p="0.000000" q="0.000000" />
            <point x="1.165321" y="-1.381896" z="0.014893" nx="0.673739" ny="-0.736569" nz="0.059482" s="2.699900" t="0.000452" p="0.000000" q="0.000000" />
            <point x="4.176630" y="-1.030612" z="0.003652" nx="0.205869" ny="-0.041307" nz="0.977707" s="2.999901" t="0.000452" p="0.000000" q="0.000000" />
            <point x="3.833883" y="-0.945289" z="0.081196" nx="0.278948" ny="-0.058874" nz="0.958500" s="-0.001600" t="0.007236" p="0.000001" q="0.000000" />
            <point x="1.670080" y="0.680067" z="0.074894" nx="0.723966" ny="0.687796" nz="0.047974" s="0.298400" t="0.007236" p="0.000001" q="0.000000" />
            <point x="1.161318" y="1.868892" z="0.065854" nx="0.688359" ny="0.448620" nz="0.514364" s="0.598400" t="0.007236" p="0.000001" q="0.000000" />
            <point x="-0.265568" y="3.673110" z="0.054835" nx="-0.062756" ny="0.324627" nz="0.935021" s="0.898400" t="0.007236" p="0.000001" q="0.000000" />
            <point x="-1.161938" y="1.378934" z="0.080031" nx="-0.907339" ny="0.416264" nz="0.053054" s="1.198400" t="0.007236" p="0.000001" q="0.000000" />
            <point x="-1.750060" y="0.432680" z="0.091325" nx="-0.789492" ny="0.611236" nz="0.050498" s="1.498400" t="0.007236" p="0.000001" q="0.000000" />
            <point x="-3.250663" y="-1.321732" z="0.113956" nx="-0.334212" ny="-0.128799" nz="0.933656" s="1.798400" t="0.007236" p="0.000001" q="0.000000" />
            <point x="-0.951377" y="-1.530316" z="0.106423" nx="-0.623833" ny="-0.778644" nz="0.067064" s="2.098400" t="0.007236" p="0.000001" q="0.000000" />
            <point x="0.301865" y="-4.166906" z="0.125958" nx="0.024173" ny="-0.270270" nz="0.962481" s="2.398400" t="0.007236" p="0.000001" q="0.000000" />
            <point x="1.162386" y="-1.377421" z="0.096268" nx="0.672960" ny="-0.736911" nz="0.063896" s="2.698400" t="0.007236" p="0.000001" q="0.000000" />
            <point x="3.833888" y="-0.945286" z="0.081196" nx="0.278947" ny="-0.058874" nz="0.958500" s="2.998400" t="0.007236" p="0.000001" q="0.000000" />
            <point x="2.788264" y="-0.683667" z="0.429011" nx="0.517107" ny="-0.114444" nz="0.848235" s="-0.008100" t="0.036634" p="0.000025" q="0.000000" />
            <point x="1.651719" y="0.675275" z="0.421851" nx="0.803267" ny="0.593430" nz="0.048490" s="0.291900" t="0.036634" p="0.000025" q="0.000000" />
            <point x="1.043129" y="1.679742" z="0.414374" nx="0.702163" ny="0.633315" nz="0.311586" s="0.591900" t="0.036634" p="0.000025" q="0.000000" />
            <point x="-0.195546" y="2.728072" z="0.412266" nx="-0.073412" ny="0.576514" nz="0.811676" s="0.891900" t="0.036634" p="0.000025" q="0.000000" />
            <point x="-1.146719" y="1.365985" z="0.439169" nx="-0.829735" ny="0.554640" nz="0.059592" s="1.191900" t="0.036634" p="0.000025" q="0.000000" />
            <point x="-1.727829" y="0.430994" z="0.456958" nx="-0.875907" ny="0.478503" nz="0.060232" s="1.491900" t="0.036634" p="0.000025" q="0.000000" />
            <point x="-2.427551" y="-0.984014" z="0.482184" nx="-0.576433" ny="-0.227234" nz="0.784913" s="1.791900" t="0.036634" p="0.000025" q="0.000000" />
            <point x="-0.938554" y="-1.508736" z="0.475039" nx="-0.603692" ny="-0.793701" nz="0.074548" s="2.091900" t="0.036634" p="0.000025" q="0.000000" />
            <point x="0.219008" y="-2.996856" z="0.483701" nx="0.044947" ny="-0.497310" nz="0.866408" s="2.391900" t="0.036634" p="0.000025" q="0.000000" />
            <point x="1.150122" y="-1.357760" z="0.453341" nx="0.668437" ny="-0.740884" nz="0.065442" s="2.691900" t="0.036634" p="0.000025" q="0.000000" />
            <point x="2.788267" y="-0.683664" z="0.429011" nx="0.517106" ny="-0.114444" nz="0.848236" s="2.991900" t="0.036634" p="0.000025" q="0.000000" />
            <point x="1.812138" y="-0.428060" z="1.383491" nx="0.903288" ny="-0.210621" nz="0.373748" s="-0.025600" t="0.115782" p="0.000251" q="0.000000" />
            <point x="1.604021" y="0.664591" z="1.358618" nx="0.907920" ny="0.417720" nz="0.034519" s="0.274400" t="0.115782" p="0.000251" q="0.000000" />
            <point x="0.928902" y="1.494363" z="1.350858" nx="0.562915" ny="0.820588" nz="0.098608" s="0.574400" t="0.115782" p="0.000251" q="0.000000" />
            <point x="-0.122329" y="1.848205" z="1.363977" nx="-0.066635" ny="0.935110" nz="0.347982" s="0.874400" t="0.115782" p="0.000251" q="0.000000" />
            <point x="-1.098575" y="1.332026" z="1.398853" nx="-0.675641" ny="0.734875" nz="0.058235" s="1.174400" t="0.115782" p="0.000251" q="0.000000" />
            <point x="-1.659497" y="0.429297" z="1.435175" nx="-0.958432" ny="0.276195" nz="0.071506" s="1.474400" t="0.115782" p="0.000251" q="0.000000" />
            <point x="-1.669551" y="-0.666417" z="1.464825" nx="-0.872491" ny="-0.349072" nz="0.341911" s="1.774400" t="0.115782" p="0.000251" q="0.000000" />
            <point x="-0.896792" y="-1.443846" z="1.469078" nx="-0.546960" ny="-0.832680" nz="0.086410" s="2.074400" t="0.115782" p="0.000251" q="0.000000" />
            <point x="0.147267" y="-1.860554" z="1.457802" nx="0.074963" ny="-0.900079" nz="0.429207" s="2.374400" t="0.115782" p="0.000251" q="0.000000" />
            <point x="1.120173" y="-1.298426" z="1.421763" nx="0.652520" ny="-0.755053" nz="0.063919" s="2.674400" t="0.115782" p="0.000251" q="0.000000" />
            <point x="1.812138" y="-0.428058" z="1.383491" nx="0.903288" ny="-0.210621" nz="0.373749" s="2.974401" t="0.115782" p="0.000251" q="0.000000" />
            <point x="1.611027" y="-0.310702" z="3.484380" nx="0.968227" ny="-0.231888" nz="0.091210" s="-0.062500" t="0.282672" p="0.001515" q="0.000000" />
            <point x="1.539498" y="0.673490" z="3.395108" nx="0.924293" ny="0.379990" nz="0.026365" s="0.237500" t="0.282672" p="0.001515" q="0.000000" />
            <point x="0.900940" y="1.427663" z="3.323807" nx="0.526209" ny="0.850131" nz="-0.001818" s="0.537500" t="0.282672" p="0.001515" q="0.000000" />
            <point x="-0.060938" y="1.663911" z="3.297697" nx="-0.072163" ny="0.997337" nz="0.006138" s="0.837500" t="0.282672" p="0.001515" q="0.000000" />
            <point x="-0.978690" y="1.291643" z="3.326781" nx="-0.643076" ny="0.765775" nz="0.003725" s="1.137500" t="0.282672" p="0.001515" q="0.000000" />
            <point x="-1.501798" y="0.453420" z="3.399918" nx="-0.968779" ny="0.243844" nz="0.041040" s="1.437500" t="0.282672" p="0.001515" q="0.000000" />
            <point x="-1.430512" y="-0.530757" z="3.489187" nx="-0.924190" ny="-0.368396" nz="0.097852" s="1.737500" t="0.282672" p="0.001515" q="0.000000" />
            <point x="-0.791880" y="-1.284893" z="3.560484" nx="-0.527772" ny="-0.841834" nz="0.111214" s="2.037500" t="0.282672" p="0.001515" q="0.000000" />
            <point x="0.170004" y="-1.521300" z="3.586610" nx="0.071626" ny="-0.986655" nz="0.146062" s="2.337500" t="0.282672" p="0.001515" q="0.000000" />
            <point x="1.087745" y="-1.148881" z="3.557512" nx="0.644083" ny="-0.758057" nz="0.102078" s="2.637500" t="0.282672" p="0.001515" q="0.000000" />
            <point x="1.611028" y="-0.310700" z="3.484380" nx="0.968227" ny="-0.231888" nz="0.091211" s="2.937500" t="0.282672" p="0.001515" q="0.000000" />
            <point x="1.400938" y="0.048358" z="6.959718" nx="0.969550" ny="-0.243217" nz="-0.027822" s="-0.129600" t="0.586148" p="0.005297" q="0.000000" />
            <point x="1.339972" y="0.922019" z="6.905280" nx="0.926068" ny="0.369303" nz="-0.072874" s="0.170400" t="0.586148" p="0.005297" q="0.000000" />
            <point x="0.781041" y="1.597824" z="6.934404" nx="0.530828" ny="0.842484" nz="-0.077620" s="0.470400" t="0.586148" p="0.005297" q="0.000000" />
            <point x="-0.062365" y="1.817637" z="7.035964" nx="-0.066296" ny="0.995598" nz="-0.039895" s="0.770400" t="0.586148" p="0.005297" q="0.000000" />
            <point x="-0.868091" y="1.497498" z="7.171169" nx="-0.637543" ny="0.769116" nz="0.025937" s="1.070400" t="0.586148" p="0.005297" q="0.000000" />
            <point x="-1.328379" y="0.759688" z="7.288375" nx="-0.963887" ny="0.248914" nz="0.094482" s="1.370400" t="0.586148" p="0.005297" q="0.000000" />
            <point x="-1.267413" y="-0.113974" z="7.342813" nx="-0.919851" ny="-0.365731" nz="0.139293" s="1.670400" t="0.586148" p="0.005297" q="0.000000" />
            <point x="-0.708481" y="-0.789778" z="7.313689" nx="-0.522504" ny="-0.839040" nz="0.143340" s="1.970400" t="0.586148" p="0.005297" q="0.000000" />
            <point x="0.134924" y="-1.009591" z="7.212128" nx="0.075376" ny="-0.990109" nz="0.105461" s="2.270400" t="0.586148" p="0.005297" q="0.000000" />
            <point x="0.940651" y="-0.689451" z="7.076923" nx="0.644974" ny="-0.762238" nz="0.040154" s="2.570400" t="0.586148" p="0.005297" q="0.000000" />
            <point x="1.400938" y="0.048359" z="6.959718" nx="0.969550" ny="-0.243217" nz="-0.027822" s="2.870400" t="0.586148" p="0.005297" q="0.000000" />
            <point x="2.087037" y="0.509746" z="12.900291" nx="0.957258" ny="-0.253140" nz="-0.139917" s="-0.240100" t="1.085911" p="0.012397" q="0.000000" />
            <point x="2.035836" y="1.298142" z="12.868011" nx="0.916308" ny="0.362148" nz="-0.170139" s="0.059900" t="1.085911" p="0.012397" q="0.000000" />
            <point x="1.540644" y="1.910480" z="12.939138" nx="0.526806" ny="0.839718" nz="-0.128816" s="0.359900" t="1.085911" p="0.012397" q="0.000000" />
            <point x="0.790608" y="2.112867" z="13.086505" nx="-0.062732" ny="0.997160" nz="-0.031368" s="0.659900" t="1.085911" p="0.012397" q="0.000000" />
            <point x="0.072217" y="1.828000" z="13.253821" nx="-0.627130" ny="0.774041" nz="0.085359" s="0.959900" t="1.085911" p="0.012397" q="0.000000" />
            <point x="-0.340130" y="1.164686" z="13.377178" nx="-0.950557" ny="0.255411" nz="0.176653" s="1.259900" t="1.085911" p="0.012397" q="0.000000" />
            <point x="-0.288929" y="0.376290" z="13.409458" nx="-0.909329" ny="-0.360454" nz="0.207198" s="1.559900" t="1.085911" p="0.012397" q="0.000000" />
            <point x="0.206263" y="-0.236047" z="13.338331" nx="-0.519332" ny="-0.838044" nz="0.165171" s="1.859900" t="1.085911" p="0.012397" q="0.000000" />
            <point x="0.956299" y="-0.438435" z="13.190965" nx="0.070235" ny="-0.994922" nz="0.066965" s="2.159900" t="1.085911" p="0.012397" q="0.000000" />
            <point x="1.674691" y="-0.153566" z="13.023648" nx="0.634155" ny="-0.771433" nz="-0.049527" s="2.459900" t="1.085911" p="0.012397" q="0.000000" />
            <point x="2.087037" y="0.509748" z="12.900291" nx="0.957258" ny="-0.253140" nz="-0.139917" s="2.759901" t="1.085911" p="0.012397" q="0.000000" />
            <point x="3.853334" y="1.039979" z="21.944016" nx="0.940389" ny="-0.254073" nz="-0.224537" s="-0.409600" t="1.852517" p="0.022599" q="0.000000" />
            <point x="3.799817" y="1.740108" z="21.894449" nx="0.895857" ny="0.360057" nz="-0.260373" s="-0.109600" t="1.852517" p="0.022599" q="0.000000" />
            <point x="3.364681" y="2.285865" z="21.985598" nx="0.511457" ny="0.837388" nz="-0.190525" s="0.190400" t="1.852517" p="0.022599" q="0.000000" />
            <point x="2.714135" y="2.468790" z="22.182650" nx="-0.066305" ny="0.995896" nz="-0.041189" s="0.490400" t="1.852517" p="0.022599" q="0.000000" />
            <point x="2.096663" y="2.219010" z="22.410336" nx="-0.617003" ny="0.774713" nz="0.131037" s="0.790400" t="1.852517" p="0.022599" q="0.000000" />
            <point x="1.748120" y="1.631934" z="22.581688" nx="-0.930137" ny="0.257837" nz="0.260158" s="1.090400" t="1.852517" p="0.022599" q="0.000000" />
            <point x="1.801637" y="0.931805" z="22.631254" nx="-0.885752" ny="-0.357292" nz="0.296282" s="1.390400" t="1.852517" p="0.022599" q="0.000000" />
            <point x="2.236773" y="0.386048" z="22.540106" nx="-0.500728" ny="-0.835224" nz="0.225468" s="1.690400" t="1.852517" p="0.022599" q="0.000000" />
            <point x="2.887320" y="0.203124" z="22.343054" nx="0.077566" ny="-0.993104" nz="0.075246" s="1.990400" t="1.852517" p="0.022599" q="0.000000" />
            <point x="3.504791" y="0.452904" z="22.115368" nx="0.627970" ny="-0.770932" nz="-0.096560" s="2.290400" t="1.852517" p="0.022599" q="0.000000" />
            <point x="3.853334" y="1.039980" z="21.944016" nx="0.940389" ny="-0.254073" nz="-0.224537" s="2.590400" t="1.852517" p="0.022599" q="0.000000" />
            <point x="7.877817" y="2.355071" z="35.064720" nx="0.960819" ny="-0.248456" nz="-0.112988" s="-0.656100" t="2.967374" p="0.034801" q="0.000000" />
            <point x="7.841994" y="2.889823" z="35.046101" nx="0.919375" ny="0.365557" nz="-0.144086" s="-0.356100" t="2.967374" p="0.034801" q="0.000000" />
            <point x="7.499073" y="3.302103" z="35.050743" nx="0.526676" ny="0.839616" nz="-0.106923" s="-0.056100" t="2.967374" p="0.034801" q="0.000000" />
            <point x="6.980039" y="3.434432" z="35.076878" nx="-0.065276" ny="0.991812" nz="-0.015959" s="0.243900" t="2.967374" p="0.034801" q="0.000000" />
            <point x="6.483145" y="3.236265" z="35.114517" nx="-0.628977" ny="0.765665" nz="0.093695" s="0.543900" t="2.967374" p="0.034801" q="0.000000" />
            <point x="6.198188" y="2.783297" z="35.149292" nx="-0.950260" ny="0.249425" nz="0.180194" s="0.843900" t="2.967374" p="0.034801" q="0.000000" />
            <point x="6.234012" y="2.248544" z="35.167912" nx="-0.908523" ny="-0.360232" nz="0.210890" s="1.143900" t="2.967374" p="0.034801" q="0.000000" />
            <point x="6.576932" y="1.836265" z="35.163269" nx="-0.519857" ny="-0.832629" nz="0.174261" s="1.443900" t="2.967374" p="0.034801" q="0.000000" />
            <point x="7.095967" y="1.703936" z="35.137135" nx="0.069313" ny="-0.988155" nz="0.084028" s="1.743900" t="2.967374" p="0.034801" q="0.000000" />
            <point x="7.592861" y="1.902103" z="35.099495" nx="0.635326" ny="-0.765726" nz="-0.025708" s="2.043900" t="2.967374" p="0.034801" q="0.000000" />
            <point x="7.877818" y="2.355072" z="35.064720" nx="0.960819" ny="-0.248456" nz="-0.112988" s="2.343901" t="2.967374" p="0.034801" q="0.000000" />
            <point x="8.208206" y="3.293083" z="54.022186" nx="0.951787" ny="-0.275056" nz="-0.002978" s="-1.000000" t="4.522747" p="0.052270" q="0.000000" />
            <point x="8.208209" y="3.315812" z="54.020908" nx="0.945739" ny="0.272896" nz="-0.024379" s="-0.700000" t="4.522747" p="0.052270" q="0.000000" />
            <point x="8.196225" y="3.333867" z="54.013935" nx="0.567018" ny="0.709702" nz="-0.022034" s="-0.400000" t="4.522747" p="0.052270" q="0.000000" />
            <point x="8.176833" y="3.340352" z="54.003929" nx="-0.027007" ny="0.865912" nz="0.006012" s="-0.100000" t="4.522747" p="0.052270" q="0.000000" />
            <point x="8.157439" y="3.332791" z="53.994713" nx="-0.602926" ny="0.693071" nz="0.049924" s="0.200000" t="4.522747" p="0.052270" q="0.000000" />
            <point x="8.145452" y="3.314070" z="53.989807" nx="-0.949448" ny="0.266709" nz="0.090617" s="0.500000" t="4.522747" p="0.052270" q="0.000000" />
            <point x="8.145450" y="3.291342" z="53.991085" nx="-0.946123" ny="-0.255638" nz="0.110238" s="0.800000" t="4.522747" p="0.052270" q="0.000000" />
            <point x="8.157434" y="3.273287" z="53.998058" nx="-0.592861" ny="-0.687288" nz="0.102187" s="1.100000" t="4.522747" p="0.052270" q="0.000000" />
            <point x="8.176826" y="3.266801" z="54.008064" nx="-0.011851" ny="-0.865917" nz="0.072393" s="1.400000" t="4.522747" p="0.052270" q="0.000000" />
            <point x="8.196219" y="3.274363" z="54.017281" nx="0.581487" ny="-0.712088" nz="0.033108" s="1.700000" t="4.522747" p="0.052270" q="0.000000" />
            <point x="8.208206" y="3.293083" z="54.022186" nx="0.951787" ny="-0.275056" nz="-0.002978" s="2.000000" t="4.522747" p="0.052270" q="0.000000" />
            <point x="7.450918" y="2.540417" z="43.968857" nx="-0.308339" ny="-0.941439" nz="0.136448" s="0.000000" t="-179.734741" p="0.042953" q="0.000000" />
            <point x="7.943783" y="3.007351" z="43.994003" nx="0.947925" ny="0.248282" nz="0.199484" s="0.666667" t="-179.734741" p="0.042953" q="0.000000" />
            <point x="7.313592" y="3.187887" z="43.815559" nx="-0.658554" ny="0.708748" nz="-0.252948" s="1.333333" t="-179.734741" p="0.042953" q="0.000000" />
            <point x="7.450918" y="2.540417" z="43.968857" nx="-0.308339" ny="-0.941439" nz="0.136448" s="2.000000" t="-179.734741" p="0.042953" q="0.000000" />
            <point x="6.247455" y="3.718891" z="49.380333" nx="-0.342592" ny="-0.899433" nz="0.250642" s="-0.333333" t="-179.090576" p="0.046877" q="0.000000" />
            <point x="6.560665" y="3.982808" z="49.352356" nx="0.929049" ny="0.249524" nz="0.218562" s="0.333333" t="-179.090576" p="0.046877" q="0.000000" />
            <point x="6.204182" y="4.066923" z="49.166943" nx="-0.609416" ny="0.680576" nz="-0.402463" s="1.000000" t="-179.090576" p="0.046877" q="0.000000" />
            <point x="6.247455" y="3.718891" z="49.380333" nx="-0.342592" ny="-0.899433" nz="0.250642" s="1.666667" t="-179.090576" p="0.046877" q="0.000000" />
            <point x="4.508718" y="6.445374" z="53.960285" nx="-0.382573" ny="-0.850132" nz="0.357101" s="-0.666667" t="-178.446426" p="0.051447" q="0.000000" />
            <point x="4.650585" y="6.557987" z="53.938904" nx="0.950339" ny="0.238710" nz="0.197468" s="0.000000" t="-178.446426" p="0.051447" q="0.000000" />
            <point x="4.486451" y="6.604861" z="53.874653" nx="-0.583122" ny="0.639674" nz="-0.499966" s="0.666667" t="-178.446426" p="0.051447" q="0.000000" />
            <point x="4.508718" y="6.445374" z="53.960285" nx="-0.382573" ny="-0.850132" nz="0.357101" s="1.333333" t="-178.446426" p="0.051447" q="0.000000" />
            <point x="3.335764" y="8.992107" z="58.814636" nx="-0.205260" ny="-0.798770" nz="0.369461" s="-1.000000" t="-177.802261" p="0.061721" q="0.000000" />
            <point x="3.336174" y="8.992478" z="58.814663" nx="0.770513" ny="0.144189" nz="0.135721" s="-0.333333" t="-177.802261" p="0.061721" q="0.000000" />
            <point x="3.335649" y="8.992641" z="58.814724" nx="-0.570464" ny="0.662091" nz="-0.452912" s="0.333333" t="-177.802261" p="0.061721" q="0.000000" />
            <point x="3.335764" y="8.992107" z="58.814636" nx="-0.205260" ny="-0.798770" nz="0.369461" s="1.000000" t="-177.802261" p="0.061721" q="0.000000" />
            <point x="1.660593" y="1.114372" z="21.364847" nx="-0.943975" ny="-0.145334" nz="0.296269" s="0.000000" t="-514.722900" p="0.021316" q="0.000000" />
            <point x="3.241111" y="0.690038" z="21.410929" nx="0.727767" ny="-0.587881" nz="0.353162" s="0.666667" t="-514.722900" p="0.021316" q="0.000000" />
            <point x="2.773515" y="2.015336" z="20.571192" nx="0.233550" ny="0.811782" nz="-0.535188" s="1.333333" t="-514.722900" p="0.021316" q="0.000000" />
            <point x="1.660593" y="1.114372" z="21.364847" nx="-0.943975" ny="-0.145334" nz="0.296269" s="2.000000" t="-514.722900" p="0.021316" q="0.000000" />
            <point x="3.228771" y="6.446828" z="28.977211" nx="-0.898056" ny="-0.171507" nz="0.219486" s="0.333333" t="-513.632996" p="0.040039" q="0.000000" />
            <point x="4.169557" y="6.556315" z="29.262800" nx="0.733174" ny="-0.354806" nz="0.568082" s="1.000000" t="-513.632996" p="0.040039" q="0.000000" />
            <point x="3.895909" y="6.820542" z="28.349604" nx="0.151014" ny="0.622361" nz="-0.736066" s="1.666667" t="-513.632996" p="0.040039" q="0.000000" />
            <point x="3.228771" y="6.446828" z="28.977211" nx="-0.898056" ny="-0.171507" nz="0.219486" s="2.333333" t="-513.632996" p="0.040039" q="0.000000" />
            <point x="1.562694" y="15.279540" z="32.032932" nx="-0.925244" ny="-0.244416" nz="0.218137" s="0.666667" t="-512.543091" p="0.061846" q="0.000000" />
            <point x="1.993502" y="15.249804" z="32.114674" nx="0.724057" ny="-0.221250" nz="0.647497" s="1.333333" t="-512.543091" p="0.061846" q="0.000000" />
            <point x="1.848488" y="15.511236" z="31.792517" nx="0.191558" ny="0.539195" nz="-0.813432" s="2.000000" t="-512.543091" p="0.061846" q="0.000000" />
            <point x="1.562694" y="15.279540" z="32.032932" nx="-0.925244" ny="-0.244416" nz="0.218137" s="2.666667" t="-512.543091" p="0.061846" q="0.000000" />
            <point x="1.132449" y="22.542763" z="38.120510" nx="0.266686" ny="-0.166952" nz="0.218042" s="1.000000" t="-511.453217" p="0.110869" q="0.000000" />
            <point x="1.133736" y="22.542786" z="38.120167" nx="-0.064974" ny="-0.459175" nz="0.548313" s="1.666667" t="-511.453217" p="0.110869" q="0.000000" />
            <point x="1.133314" y="22.543488" z="38.121220" nx="-0.202477" ny="0.624983" nz="-0.717342" s="2.333333" t="-511.453217" p="0.110869" q="0.000000" />
            <point x="1.132449" y="22.542763" z="38.120510" nx="0.266686" ny="-0.166952" nz="0.218042" s="3.000000" t="-511.453217" p="0.110869" q="0.000000" />
            <point x="6.193850" y="1.578148" z="31.121038" nx="0.621713" ny="-0.775107" nz="0.112589" s="0.000000" t="-123.200630" p="0.030959" q="0.000000" />
            <point x="5.970242" y="2.908360" z="31.144440" nx="0.334235" ny="0.931131" nz="0.145800" s="0.666667" t="-123.200630" p="0.030959" q="0.000000" />
            <point x="4.947788" y="2.056255" z="30.924175" nx="-0.976266" ny="-0.161575" nz="-0.144085" s="1.333333" t="-123.200630" p="0.030959" q="0.000000" />
            <point x="6.193850" y="1.578148" z="31.121038" nx="0.621713" ny="-0.775107" nz="0.112589" s="2.000000" t="-123.200630" p="0.030959" q="0.000000" />
            <point x="4.427964" y="1.445632" z="39.959888" nx="0.574497" ny="-0.775323" nz="-0.130594" s="-0.333333" t="-122.142799" p="0.038717" q="0.000000" />
            <point x="4.232976" y="2.076824" z="40.437504" nx="0.320156" ny="0.834952" nz="0.441658" s="0.333333" t="-122.142799" p="0.038717" q="0.000000" />
            <point x="3.667102" y="1.738250" z="39.958241" nx="-0.916320" ny="-0.108071" nz="-0.231268" s="1.000000" t="-122.142799" p="0.038717" q="0.000000" />
            <point x="4.427964" y="1.445632" z="39.959888" nx="0.574497" ny="-0.775323" nz="-0.130594" s="1.666667" t="-122.142799" p="0.038717" q="0.000000" />
            <point x="2.004958" y="-4.162759" z="46.776829" nx="0.678922" ny="-0.594517" nz="-0.429578" s="-0.666667" t="-121.084976" p="0.047752" q="0.000000" />
            <point x="1.910400" y="-3.951015" z="47.055019" nx="0.259260" ny="0.591271" nz="0.757516" s="0.000000" t="-121.084976" p="0.047752" q="0.000000" />
            <point x="1.656933" y="-4.077357" z="46.829281" nx="-0.949251" ny="-0.055819" nz="-0.280168" s="0.666667" t="-121.084976" p="0.047752" q="0.000000" />
            <point x="2.004958" y="-4.162759" z="46.776829" nx="0.678922" ny="-0.594517" nz="-0.429578" s="1.333333" t="-121.084976" p="0.047752" q="0.000000" />
            <point x="0.832671" y="-11.507443" z="52.204250" nx="-0.052348" ny="-0.372690" nz="-0.515652" s="-1.000000" t="-120.027145" p="0.068063" q="0.000000" />
            <point x="0.832430" y="-11.506538" z="52.203678" nx="0.111634" ny="0.539274" nz="0.814744" s="-0.333333" t="-120.027145" p="0.068063" q="0.000000" />
            <point x="0.831629" y="-11.507107" z="52.204170" nx="-0.060677" ny="-0.174850" nz="-0.251014" s="0.333333" t="-120.027145" p="0.068063" q="0.000000" />
            <point x="0.832671" y="-11.507443" z="52.204250" nx="-0.052348" ny="-0.372690" nz="-0.515652" s="1.000000" t="-120.027145" p="0.068063" q="0.000000" />
            <point x="3.461102" y="1.852221" z="21.782341" nx="0.833186" ny="0.551290" nz="0.042630" s="0.000000" t="141.196686" p="0.022053" q="0.000000" />
            <point x="1.975727" y="1.507957" z="22.337828" nx="-0.751053" ny="0.185247" nz="0.633687" s="0.666667" t="141.196686" p="0.022053" q="0.000000" />
            <point x="2.655945" y="0.567624" z="21.203588" nx="-0.024450" ny="-0.819142" nz="-0.573044" s="1.333333" t="141.196686" p="0.022053" q="0.000000" />
            <point x="3.461102" y="1.852221" z="21.782341" nx="0.833186" ny="0.551290" nz="0.042630" s="2.000000" t="141.196686" p="0.022053" q="0.000000" />
            <point x="6.439816" y="-3.097908" z="27.579491" nx="0.907138" ny="0.409620" nz="0.058095" s="0.333333" t="142.119598" p="0.035706" q="0.000000" />
            <point x="5.507503" y="-3.135170" z="27.881058" nx="-0.696428" ny="0.245184" nz="0.655497" s="1.000000" t="142.119598" p="0.035706" q="0.000000" />
            <point x="5.788369" y="-3.645278" z="27.092106" nx="-0.175107" ny="-0.750559" nz="-0.634095" s="1.666667" t="142.119598" p="0.035706" q="0.000000" />
            <point x="6.439816" y="-3.097908" z="27.579491" nx="0.907138" ny="0.409620" nz="0.058095" s="2.333333" t="142.119598" p="0.035706" q="0.000000" />
            <point x="7.916848" y="-9.499582" z="32.247086" nx="0.920720" ny="0.275450" nz="0.154851" s="0.666667" t="143.042526" p="0.051608" q="0.000000" />
            <point x="7.489305" y="-9.425106" z="32.285133" nx="-0.729181" ny="0.427768" nz="0.529030" s="1.333333" t="143.042526" p="0.051608" q="0.000000" />
            <point x="7.630723" y="-9.783998" z="32.082684" nx="-0.186367" ny="-0.764742" nz="-0.597278" s="2.000000" t="143.042526" p="0.051608" q="0.000000" />
            <point x="7.916848" y="-9.499582" z="32.247086" nx="0.920720" ny="0.275450" nz="0.154851" s="2.666667" t="143.042526" p="0.051608" q="0.000000" />
            <point x="7.610162" y="-13.535576" z="39.187424" nx="0.072449" ny="0.292837" nz="0.173494" s="1.000000" t="143.965439" p="0.087357" q="0.000000" />
            <point x="7.608882" y="-13.535543" z="39.187099" nx="-0.167192" ny="0.579028" nz="0.347735" s="1.666667" t="143.965439" p="0.087357" q="0.000000" />
            <point x="7.609284" y="-13.536258" z="39.188137" nx="0.092907" ny="-0.857604" nz="-0.452605" s="2.333333" t="143.965439" p="0.087357" q="0.000000" />
            <point x="7.610162" y="-13.535576" z="39.187424" nx="0.072449" ny="0.292837" nz="0.173494" s="3.000000" t="143.965439" p="0.087357" q="0.000000" />
            <point x="5.297410" y="2.873240" z="30.503166" nx="-0.314191" ny="0.944077" nz="-0.100009" s="0.000000" t="337.269257" p="0.030529" q="0.000000" />
            <point x="5.075974" y="1.594530" z="30.918640" nx="-0.594679" ny="-0.679468" nz="0.429744" s="0.666667" t="337.269257" p="0.030529" q="0.000000" />
            <point x="6.289883" y="1.944427" z="30.408001" nx="0.947468" ny="-0.234681" nz="-0.217311" s="1.333333" t="337.269257" p="0.030529" q="0.000000" />
            <point x="5.297410" y="2.873240" z="30.503166" nx="-0.314191" ny="0.944077" nz="-0.100009" s="2.000000" t="337.269257" p="0.030529" q="0.000000" />
            <point x="7.932755" y="4.533200" z="37.893768" nx="-0.290137" ny="0.932480" nz="-0.110504" s="-0.333333" t="338.190247" p="0.048606" q="0.000000" />
            <point x="7.864411" y="3.805933" z="38.273727" nx="-0.533944" ny="-0.624626" nz="0.562241" s="0.333333" t="338.190247" p="0.048606" q="0.000000" />
            <point x="8.455420" y="3.923324" z="37.712582" nx="0.883805" ny="-0.274884" nz="-0.367175" s="1.000000" t="338.190247" p="0.048606" q="0.000000" />
            <point x="7.932755" y="4.533200" z="37.893768" nx="-0.290137" ny="0.932480" nz="-0.110504" s="1.666667" t="338.190247" p="0.048606" q="0.000000" />
            <point x="12.968689" y="6.820983" z="43.674278" nx="-0.339554" ny="0.902524" nz="-0.128933" s="-0.666667" t="339.111267" p="0.069660" q="0.000000" />
            <point x="12.918159" y="6.478262" z="43.791767" nx="-0.542179" ny="-0.629411" nz="0.535084" s="0.000000" t="339.111267" p="0.069660" q="0.000000" />
            <point x="13.250710" y="6.588319" z="43.686359" nx="0.909578" ny="-0.245734" nz="-0.325622" s="0.666667" t="339.111267" p="0.069660" q="0.000000" />
            <point x="12.968689" y="6.820983" z="43.674278" nx="-0.339554" ny="0.902524" nz="-0.128933" s="1.333333" t="339.111267" p="0.069660" q="0.000000" />
            <point x="14.649675" y="8.963323" z="51.214870" nx="-0.116834" ny="0.734252" nz="-0.182561" s="-1.000000" t="340.032288" p="0.116991" q="0.000000" />
            <point x="14.649577" y="8.962374" z="51.214306" nx="-0.539393" ny="-0.746539" nz="0.375667" s="-0.333333" t="340.032288" p="0.116991" q="0.000000" />
            <point x="14.650546" y="8.962644" z="51.214771" nx="0.652998" ny="0.005717" nz="-0.123222" s="0.333333" t="340.032288" p="0.116991" q="0.000000" />
            <point x="14.649675" y="8.963323" z="51.214870" nx="-0.116834" ny="0.734252" nz="-0.182561" s="1.000000" t="340.032288" p="0.116991" q="0.000000" />
            <point x="5.919909" y="1.493761" z="31.882822" nx="-0.003733" ny="-0.967559" nz="0.252616" s="0.000000" t="-211.816483" p="0.031585" q="0.000000" />
            <point x="6.585469" y="2.625482" z="31.674118" nx="0.862956" ny="0.504738" nz="-0.023178" s="0.666667" t="-211.816483" p="0.031585" q="0.000000" />
            <point x="5.257817" y="2.613081" z="31.607000" nx="-0.865563" ny="0.489900" nz="-0.103754" s="1.333333" t="-211.816483" p="0.031585" q="0.000000" />
            <point x="5.919909" y="1.493761" z="31.882822" nx="-0.003733" ny="-0.967559" nz="0.252616" s="2.000000" t="-211.816483" p="0.031585" q="0.000000" />
            <point x="5.507720" y="3.502274" z="39.569649" nx="0.022986" ny="-0.885386" nz="0.445664" s="0.333333" t="-210.925140" p="0.043914" q="0.000000" />
            <point x="5.912362" y="4.124782" z="39.262974" nx="0.802444" ny="0.542132" nz="-0.037887" s="1.000000" t="-210.925140" p="0.043914" q="0.000000" />
            <point x="5.149020" y="3.996752" z="39.047993" nx="-0.852195" ny="0.397990" nz="-0.316563" s="1.666667" t="-210.925140" p="0.043914" q="0.000000" />
            <point x="5.507720" y="3.502274" z="39.569649" nx="0.022986" ny="-0.885386" nz="0.445664" s="2.333333" t="-210.925140" p="0.043914" q="0.000000" />
            <point x="3.108423" y="8.177856" z="45.306915" nx="-0.054677" ny="-0.754694" nz="0.653605" s="0.666667" t="-210.033783" p="0.058275" q="0.000000" />
            <point x="3.298158" y="8.432588" z="45.144184" nx="0.839763" ny="0.536726" nz="-0.074519" s="1.333333" t="-210.033783" p="0.058275" q="0.000000" />
            <point x="2.955715" y="8.382122" z="45.057266" nx="-0.810538" ny="0.274896" nz="-0.514733" s="2.000000" t="-210.033783" p="0.058275" q="0.000000" />
            <point x="3.108423" y="8.177856" z="45.306915" nx="-0.054677" ny="-0.754694" nz="0.653605" s="2.666667" t="-210.033783" p="0.058275" q="0.000000" />
            <point x="0.986509" y="13.408236" z="50.629486" nx="0.296534" ny="-0.571106" nz="0.679431" s="1.000000" t="-209.142441" p="0.090558" q="0.000000" />
            <point x="0.987018" y="13.409150" z="50.629761" nx="0.144526" ny="0.176049" nz="-0.098823" s="1.666667" t="-209.142441" p="0.090558" q="0.000000" />
            <point x="0.985994" y="13.408986" z="50.630070" nx="-0.442636" ny="0.402132" nz="-0.519188" s="2.333333" t="-209.142441" p="0.090558" q="0.000000" />
            <point x="0.986509" y="13.408236" z="50.629486" nx="0.296534" ny="-0.571106" nz="0.679431" s="3.000000" t="-209.142441" p="0.090558" q="0.000000" />
            <point x="6.947940" y="2.870225" z="41.379959" nx="-0.984639" ny="0.123203" nz="-0.123701" s="0.000000" t="-389.041229" p="0.040667" q="0.000000" />
            <point x="7.591021" y="2.399848" z="41.624088" nx="0.351433" ny="-0.854062" nz="0.383492" s="0.666667" t="-389.041229" p="0.040667" q="0.000000" />
            <point x="7.722202" y="3.177243" z="41.354172" nx="0.624034" ny="0.760916" nz="-0.177718" s="1.333333" t="-389.041229" p="0.040667" q="0.000000" />
            <point x="6.947940" y="2.870225" z="41.379959" nx="-0.984639" ny="0.123203" nz="-0.123701" s="2.000000" t="-389.041229" p="0.040667" q="0.000000" />
            <point x="6.446081" y="5.142517" z="47.637814" nx="-0.977639" ny="0.203824" nz="-0.046482" s="-0.333333" t="-388.280975" p="0.051094" q="0.000000" />
            <point x="6.818424" y="4.808704" z="47.696785" nx="0.312083" ny="-0.892016" nz="0.317167" s="0.333333" t="-388.280975" p="0.051094" q="0.000000" />
            <point x="6.923531" y="5.281221" z="47.558117" nx="0.668649" ny="0.711898" nz="-0.192055" s="1.000000" t="-388.280975" p="0.051094" q="0.000000" />
            <point x="6.446081" y="5.142517" z="47.637814" nx="-0.977639" ny="0.203824" nz="-0.046482" s="1.666667" t="-388.280975" p="0.051094" q="0.000000" />
            <point x="7.177254" y="6.859277" z="54.048824" nx="-0.915551" ny="0.294357" nz="0.267869" s="-0.666667" t="-387.520691" p="0.063238" q="0.000000" />
            <point x="7.309217" y="6.693499" z="53.977070" nx="0.279937" ny="-0.940332" nz="0.079713" s="0.000000" t="-387.520691" p="0.063238" q="0.000000" />
            <point x="7.366714" y="6.906422" z="53.939613" nx="0.662336" ny="0.651500" nz="-0.287100" s="0.666667" t="-387.520691" p="0.063238" q="0.000000" />
            <point x="7.177254" y="6.859277" z="54.048824" nx="-0.915551" ny="0.294357" nz="0.267869" s="1.333333" t="-387.520691" p="0.063238" q="0.000000" />
            <point x="10.563934" y="6.944610" z="59.731934" nx="-0.776983" ny="-0.172777" nz="0.465614" s="-1.000000" t="-386.760437" p="0.090539" q="0.000000" />
            <point x="10.564350" y="6.944120" z="59.732151" nx="0.136100" ny="-0.211300" nz="-0.067778" s="-0.333333" t="-386.760437" p="0.090539" q="0.000000" />
            <point x="10.564380" y="6.944737" z="59.732430" nx="0.633982" ny="0.381790" nz="-0.352486" s="0.333333" t="-386.760437" p="0.090539" q="0.000000" />
            <point x="10.563934" y="6.944610" z="59.731934" nx="-0.776983" ny="-0.172777" nz="0.465614" s="1.000000" t="-386.760437" p="0.090539" q="0.000000" />
            <point x="1.025477" y="0.816442" z="18.387444" nx="-0.933995" ny="-0.268806" nz="0.235333" s="0.000000" t="-412.513580" p="0.018046" q="0.000000" />
            <point x="2.701859" y="0.691233" z="18.646175" nx="0.769153" ny="-0.383824" nz="0.510871" s="0.666667" t="-412.513580" p="0.018046" q="0.000000" />
            <point x="2.094872" y="1.832549" z="17.540806" nx="0.152332" ny="0.776610" nz="-0.611171" s="1.333333" t="-412.513580" p="0.018046" q="0.000000" />
            <point x="1.025477" y="0.816442" z="18.387444" nx="-0.933995" ny="-0.268806" nz="0.235333" s="2.000000" t="-412.513580" p="0.018046" q="0.000000" />
            <point x="0.902867" y="6.304270" z="24.169220" nx="-0.856296" ny="-0.268329" nz="0.156700" s="0.333333" t="-411.592804" p="0.042386" q="0.000000" />
            <point x="1.789904" y="6.684815" z="24.522243" nx="0.682229" ny="-0.083057" nz="0.706299" s="1.000000" t="-411.592804" p="0.042386" q="0.000000" />
            <point x="1.624213" y="6.622355" z="23.509861" nx="0.126860" ny="0.478622" nz="-0.834694" s="1.666667" t="-411.592804" p="0.042386" q="0.000000" />
            <point x="0.902867" y="6.304270" z="24.169220" nx="-0.856296" ny="-0.268329" nz="0.156700" s="2.333333" t="-411.592804" p="0.042386" q="0.000000" />
            <point x="-1.997606" y="13.849445" z="24.184984" nx="-0.950688" ny="-0.239230" nz="0.197172" s="0.666667" t="-410.672028" p="0.070733" q="0.000000" />
            <point x="-1.573084" y="13.930483" z="24.332296" nx="0.619416" ny="0.241473" nz="0.738949" s="1.333333" t="-410.672028" p="0.070733" q="0.000000" />
            <point x="-1.655833" y="13.890684" z="23.885021" nx="0.306117" ny="0.105926" nz="-0.940434" s="2.000000" t="-410.672028" p="0.070733" q="0.000000" />
            <point x="-1.997606" y="13.849445" z="24.184984" nx="-0.950688" ny="-0.239230" nz="0.197172" s="2.666667" t="-410.672028" p="0.070733" q="0.000000" />
            <point x="-3.091100" y="21.774641" z="23.682158" nx="0.374223" ny="0.064524" nz="0.203164" s="1.000000" t="-409.751282" p="0.134461" q="0.000000" />
            <point x="-3.089831" y="21.774527" z="23.681620" nx="-0.000710" ny="0.060297" nz="0.728552" s="1.666667" t="-409.751282" p="0.134461" q="0.000000" />
            <point x="-3.090285" y="21.775757" z="23.682066" nx="-0.384393" ny="-0.092778" nz="-0.887741" s="2.333333" t="-409.751282" p="0.134461" q="0.000000" />
            <point x="-3.091100" y="21.774641" z="23.682158" nx="0.374223" ny="0.064524" nz="0.203164" s="3.000000" t="-409.751282" p="0.134461" q="0.000000" />
            <point x="7.563839" y="2.587656" z="44.764889" nx="-0.153993" ny="-0.987948" nz="0.015620" s="0.000000" t="-119.010277" p="0.043737" q="0.000000" />
            <point x="7.957706" y="3.074965" z="44.757874" nx="0.933575" ny="0.358204" nz="-0.010491" s="0.666667" t="-119.010277" p="0.043737" q="0.000000" />
            <point x="7.340064" y="3.171903" z="44.799953" nx="-0.772030" ny="0.625605" nz="0.112013" s="1.333333" t="-119.010277" p="0.043737" q="0.000000" />
            <point x="7.563839" y="2.587656" z="44.764889" nx="-0.153993" ny="-0.987948" nz="0.015620" s="2.000000" t="-119.010277" p="0.043737" q="0.000000" />
            <point x="7.837906" y="2.608784" z="48.803181" nx="-0.088070" ny="-0.953183" nz="-0.240619" s="-0.333333" t="-118.533852" p="0.053116" q="0.000000" />
            <point x="8.074888" y="2.890617" z="48.891373" nx="0.874463" ny="0.385759" nz="-0.032897" s="0.333333" t="-118.533852" p="0.053116" q="0.000000" />
            <point x="7.723638" y="2.887389" z="49.032722" nx="-0.759696" ny="0.526065" nz="0.360261" s="1.000000" t="-118.533852" p="0.053116" q="0.000000" />
            <point x="7.837906" y="2.608784" z="48.803181" nx="-0.088070" ny="-0.953183" nz="-0.240619" s="1.666667" t="-118.533852" p="0.053116" q="0.000000" />
            <point x="9.192306" y="0.580763" z="52.118919" nx="-0.299736" ny="-0.744381" nz="-0.550602" s="-0.666667" t="-118.057419" p="0.064039" q="0.000000" />
            <point x="9.310414" y="0.644930" z="52.220066" nx="0.970755" ny="0.200554" nz="0.128779" s="0.000000" t="-118.057419" p="0.064039" q="0.000000" />
            <point x="9.152660" y="0.702845" z="52.227646" nx="-0.677647" ny="0.490134" nz="0.480347" s="0.666667" t="-118.057419" p="0.064039" q="0.000000" />
            <point x="9.192306" y="0.580763" z="52.118919" nx="-0.299736" ny="-0.744381" nz="-0.550602" s="1.333333" t="-118.057419" p="0.064039" q="0.000000" />
            <point x="8.309706" y="-2.208097" z="55.058472" nx="-0.050324" ny="-0.710825" nz="-0.689495" s="-1.000000" t="-117.580994" p="0.088595" q="0.000000" />
            <point x="8.310093" y="-2.207790" z="55.058342" nx="0.275991" ny="0.235362" nz="0.333830" s="-0.333333" t="-117.580994" p="0.088595" q="0.000000" />
            <point x="8.309613" y="-2.207653" z="55.058235" nx="-0.231347" ny="0.466103" nz="0.410358" s="0.333333" t="-117.580994" p="0.088595" q="0.000000" />
            <point x="8.309706" y="-2.208097" z="55.058472" nx="-0.050324" ny="-0.710825" nz="-0.689495" s="1.000000" t="-117.580994" p="0.088595" q="0.000000" />
            <point x="2.533250" y="1.967325" z="23.844391" nx="-0.811925" ny="0.564997" nz="0.146784" s="0.000000" t="475.710083" p="0.023999" q="0.000000" />
            <point x="3.435813" y="0.754659" z="24.261177" nx="0.184285" ny="-0.773068" nz="0.606964" s="0.666667" t="475.710083" p="0.023999" q="0.000000" />
            <point x="3.891841" y="1.710436" z="23.104710" nx="0.689384" ny="0.284066" nz="-0.666373" s="1.333333" t="475.710083" p="0.023999" q="0.000000" />
            <point x="2.533250" y="1.967325" z="23.844391" nx="-0.811925" ny="0.564997" nz="0.146784" s="2.000000" t="475.710083" p="0.023999" q="0.000000" />
            <point x="6.924135" y="6.799396" z="29.532759" nx="-0.752834" ny="0.618337" nz="0.162480" s="0.333333" t="476.695221" p="0.036562" q="0.000000" />
            <point x="7.468873" y="6.078039" z="29.816870" nx="0.213543" ny="-0.699785" nz="0.665814" s="1.000000" t="476.695221" p="0.036562" q="0.000000" />
            <point x="7.593273" y="6.455517" z="28.956726" nx="0.612201" ny="0.157176" nz="-0.774728" s="1.666667" t="476.695221" p="0.036562" q="0.000000" />
            <point x="6.924135" y="6.799396" z="29.532759" nx="-0.752834" ny="0.618337" nz="0.162480" s="2.333333" t="476.695221" p="0.036562" q="0.000000" />
            <point x="12.855412" y="12.191027" z="32.763519" nx="-0.599606" ny="0.739973" nz="0.216730" s="0.666667" t="477.680359" p="0.051195" q="0.000000" />
            <point x="12.956674" y="11.784031" z="32.799717" nx="0.080680" ny="-0.784149" nz="0.615159" s="1.333333" t="477.680359" p="0.051195" q="0.000000" />
            <point x="13.148788" y="12.023952" z="32.512070" nx="0.587856" ny="0.077483" nz="-0.773312" s="2.000000" t="477.680359" p="0.051195" q="0.000000" />
            <point x="12.855412" y="12.191027" z="32.763519" nx="-0.599606" ny="0.739973" nz="0.216730" s="2.666667" t="477.680359" p="0.051195" q="0.000000" />
            <point x="19.040548" y="14.015645" z="38.415897" nx="-0.176125" ny="-0.362221" nz="0.309653" s="1.000000" t="478.665497" p="0.084090" q="0.000000" />
            <point x="19.040922" y="14.014435" z="38.415741" nx="-0.452415" ny="0.075677" nz="0.460080" s="1.666667" t="478.665497" p="0.084090" q="0.000000" />
            <point x="19.041327" y="14.015102" z="38.416752" nx="0.624412" ny="0.285873" nz="-0.719529" s="2.333333" t="478.665497" p="0.084090" q="0.000000" />
            <point x="19.040548" y="14.015645" z="38.415897" nx="-0.176125" ny="-0.362221" nz="0.309653" s="3.000000" t="478.665497" p="0.084090" q="0.000000" />
            <point x="7.959256" y="2.874982" z="48.056648" nx="0.575635" ny="-0.816076" nz="-0.051613" s="0.000000" t="-54.699085" p="0.046788" q="0.000000" />
            <point x="7.921680" y="3.293472" z="48.086231" nx="0.421164" ny="0.904284" nz="0.069929" s="0.666667" t="-54.699085" p="0.046788" q="0.000000" />
            <point x="7.577375" y="3.050865" z="48.082203" nx="-0.994255" ny="-0.093017" nz="0.052969" s="1.333333" t="-54.699085" p="0.046788" q="0.000000" />
            <point x="7.959256" y="2.874982" z="48.056648" nx="0.575635" ny="-0.816076" nz="-0.051613" s="2.000000" t="-54.699085" p="0.046788" q="0.000000" />
            <point x="8.049811" y="2.677516" z="52.188812" nx="0.570128" ny="-0.819697" nz="0.048839" s="-0.333333" t="-54.227135" p="0.055440" q="0.000000" />
            <point x="8.028932" y="2.928894" z="52.154835" nx="0.419826" ny="0.904415" nz="-0.005267" s="0.333333" t="-54.227135" p="0.055440" q="0.000000" />
            <point x="7.819868" y="2.784119" z="52.165512" nx="-0.991461" ny="-0.079249" nz="0.022955" s="1.000000" t="-54.227135" p="0.055440" q="0.000000" />
            <point x="8.049811" y="2.677516" z="52.188812" nx="0.570128" ny="-0.819697" nz="0.048839" s="1.666667" t="-54.227135" p="0.055440" q="0.000000" />
            <point x="7.839841" y="3.279499" z="56.239979" nx="0.579291" ny="-0.767878" nz="0.089257" s="-0.666667" t="-53.755184" p="0.065516" q="0.000000" />
            <point x="7.823651" y="3.386262" z="56.206425" nx="0.402340" ny="0.854044" nz="-0.280381" s="0.000000" t="-53.755184" p="0.065516" q="0.000000" />
            <point x="7.744297" y="3.333470" z="56.267273" nx="-0.964324" ny="-0.070803" nz="0.240008" s="0.666667" t="-53.755184" p="0.065516" q="0.000000" />
            <point x="7.839841" y="3.279499" z="56.239979" nx="0.579291" ny="-0.767878" nz="0.089257" s="1.333333" t="-53.755184" p="0.065516" q="0.000000" />
            <point x="9.554939" y="4.685709" z="59.696793" nx="0.248356" ny="-0.427298" nz="0.050600" s="-1.000000" t="-53.283237" p="0.088168" q="0.000000" />
            <point x="9.554906" y="4.686041" z="59.696869" nx="0.490807" ny="0.609400" nz="-0.470369" s="-0.333333" t="-53.283237" p="0.088168" q="0.000000" />
            <point x="9.554652" y="4.685875" z="59.696709" nx="-0.736827" ny="-0.179258" nz="0.459652" s="0.333333" t="-53.283237" p="0.088168" q="0.000000" />
            <point x="9.554939" y="4.685709" z="59.696793" nx="0.248356" ny="-0.427298" nz="0.050600" s="1.000000" t="-53.283237" p="0.088168" q="0.000000" />
            <point x="2.466738" y="0.331555" z="21.124292" nx="-0.129546" ny="-0.990034" nz="0.055103" s="0.000000" t="-221.444946" p="0.021300" q="0.000000" />
            <point x="3.135717" y="1.707228" z="21.708416" nx="0.577534" ny="0.463437" nz="0.672065" s="0.666667" t="-221.444946" p="0.021300" q="0.000000" />
            <point x="2.063949" y="1.778682" z="20.472528" nx="-0.554758" ny="0.538923" nz="-0.633875" s="1.333333" t="-221.444946" p="0.021300" q="0.000000" />
            <point x="2.466738" y="0.331555" z="21.124292" nx="-0.129546" ny="-0.990034" nz="0.055103" s="2.000000" t="-221.444946" p="0.021300" q="0.000000" />
            <point x="-3.422391" y="1.392072" z="26.333292" nx="-0.057695" ny="-0.994613" nz="0.045073" s="0.333333" t="-220.526871" p="0.040933" q="0.000000" />
            <point x="-3.175206" y="2.251764" z="26.756161" nx="0.496525" ny="0.505970" nz="0.705134" s="1.000000" t="-220.526871" p="0.040933" q="0.000000" />
            <point x="-3.714639" y="2.245468" z="25.926725" nx="-0.546372" ny="0.489082" nz="-0.674926" s="1.666667" t="-220.526871" p="0.040933" q="0.000000" />
            <point x="-3.422391" y="1.392072" z="26.333292" nx="-0.057695" ny="-0.994613" nz="0.045073" s="2.333333" t="-220.526871" p="0.040933" q="0.000000" />
            <point x="-10.182940" y="1.500938" z="30.736893" nx="-0.135893" ny="-0.971384" nz="0.077423" s="0.666667" t="-219.608780" p="0.063799" q="0.000000" />
            <point x="-9.929164" y="1.853725" z="30.803015" nx="0.618790" ny="0.478603" nz="0.621542" s="1.333333" t="-219.608780" p="0.063799" q="0.000000" />
            <point x="-10.281039" y="1.882074" z="30.541075" nx="-0.552623" ny="0.513618" nz="-0.619394" s="2.000000" t="-219.608780" p="0.063799" q="0.000000" />
            <point x="-10.182940" y="1.500938" z="30.736893" nx="-0.135893" ny="-0.971384" nz="0.077423" s="2.666667" t="-219.608780" p="0.063799" q="0.000000" />
            <point x="-14.632121" y="3.807492" z="36.962856" nx="0.150081" ny="-0.235421" nz="0.194468" s="1.000000" t="-218.690704" p="0.115203" q="0.000000" />
            <point x="-14.631271" y="3.808514" z="36.962753" nx="0.488383" ny="-0.237841" nz="0.448292" s="1.666667" t="-218.690704" p="0.115203" q="0.000000" />
            <point x="-14.632287" y="3.808575" z="36.963612" nx="-0.634459" ny="0.470257" nz="-0.570902" s="2.333333" t="-218.690704" p="0.115203" q="0.000000" />
            <point x="-14.632121" y="3.807492" z="36.962856" nx="0.150081" ny="-0.235421" nz="0.194468" s="3.000000" t="-218.690704" p="0.115203" q="0.000000" />
            <point x="2.083420" y="0.159729" z="16.330765" nx="0.480837" ny="-0.875890" nz="-0.039020" s="0.000000" t="-109.873024" p="0.016053" q="0.000000" />
            <point x="1.828086" y="1.702752" z="17.092596" nx="0.228349" ny="0.658704" nz="0.716901" s="0.666667" t="-109.873024" p="0.016053" q="0.000000" />
            <point x="0.781073" y="1.185417" z="15.803166" nx="-0.810829" ny="0.145685" nz="-0.566828" s="1.333333" t="-109.873024" p="0.016053" q="0.000000" />
            <point x="2.083420" y="0.159729" z="16.330765" nx="0.480837" ny="-0.875890" nz="-0.039020" s="2.000000" t="-109.873024" p="0.016053" q="0.000000" />
            <point x="-2.593015" y="-2.630736" z="21.342022" nx="0.612296" ny="-0.776812" nz="-0.087582" s="-0.333333" t="-109.003601" p="0.035045" q="0.000000" />
            <point x="-3.041675" y="-1.915355" z="21.968121" nx="0.064453" ny="0.613868" nz="0.782594" s="0.333333" t="-109.003601" p="0.035045" q="0.000000" />
            <point x="-3.488220" y="-2.163753" z="21.049448" nx="-0.763281" ny="0.062809" nz="-0.618732" s="1.000000" t="-109.003601" p="0.035045" q="0.000000" />
            <point x="-2.593015" y="-2.630736" z="21.342024" nx="0.612296" ny="-0.776812" nz="-0.087582" s="1.666667" t="-109.003601" p="0.035045" q="0.000000" />
            <point x="-6.769311" y="-7.767126" z="24.747810" nx="0.855436" ny="-0.428613" nz="-0.183001" s="-0.666667" t="-108.134178" p="0.057165" q="0.000000" />
            <point x="-7.019009" y="-7.521900" z="25.057056" nx="-0.027521" ny="0.550083" nz="0.762152" s="0.000000" t="-108.134178" p="0.057165" q="0.000000" />
            <point x="-7.231936" y="-7.825767" z="24.773430" nx="-0.831779" ny="-0.214899" nz="-0.501202" s="0.666667" t="-108.134178" p="0.057165" q="0.000000" />
            <point x="-6.769311" y="-7.767126" z="24.747810" nx="0.855436" ny="-0.428613" nz="-0.183001" s="1.333333" t="-108.134178" p="0.057165" q="0.000000" />
            <point x="-6.028124" y="-13.178776" z="29.989573" nx="0.024145" ny="-0.363131" nz="-0.378315" s="-1.000000" t="-107.264755" p="0.106892" q="0.000000" />
            <point x="-6.028903" y="-13.177793" z="29.988916" nx="0.128760" ny="0.663276" nz="0.734800" s="-0.333333" t="-107.264755" p="0.106892" q="0.000000" />
            <point x="-6.029524" y="-13.178730" z="29.989777" nx="-0.150814" ny="-0.305781" nz="-0.279025" s="0.333333" t="-107.264755" p="0.106892" q="0.000000" />
            <point x="-6.028124" y="-13.178776" z="29.989573" nx="0.024145" ny="-0.363131" nz="-0.378315" s="1.000000" t="-107.264755" p="0.106892" q="0.000000" />
        </vertexs>
        <strips num="1">
            <strip num="656">
                <ind val="11" />
                <ind val="0" />
                <ind val="12" />
                <ind val="1" />
                <ind val="13" />
                <ind val="2" />
                <ind val="14" />
                <ind val="3" />
                <ind val="15" />
                <ind val="4" />
                <ind val="16" />
                <ind val="5" />
                <ind val="17" />
                <ind val="6" />
                <ind val="18" />
                <ind val="7" />
                <ind val="19" />
                <ind val="8" />
                <ind val="20" />
                <ind val="9" />
                <ind val="21" />
                <ind val="10" />
                <ind val="11" />
                <ind val="11" />
                <ind val="22" />
                <ind val="11" />
                <ind val="23" />
                <ind val="12" />
                <ind val="24" />
                <ind val="13" />
                <ind val="25" />
                <ind val="14" />
                <ind val="26" />
                <ind val="15" />
                <ind val="27" />
                <ind val="16" />
                <ind val="28" />
                <ind val="17" />
                <ind val="29" />
                <ind val="18" />
                <ind val="30" />
                <ind val="19" />
                <ind val="31" />
                <ind val="20" />
                <ind val="32" />
                <ind val="21" />
                <ind val="22" />
                <ind val="22" />
                <ind val="33" />
                <ind val="22" />
                <ind val="34" />
                <ind val="23" />
                <ind val="35" />
                <ind val="24" />
                <ind val="36" />
                <ind val="25" />
                <ind val="37" />
                <ind val="26" />
                <ind val="38" />
                <ind val="27" />
                <ind val="39" />
                <ind val="28" />
                <ind val="40" />
                <ind val="29" />
                <ind val="41" />
                <ind val="30" />
                <ind val="42" />
                <ind val="31" />
                <ind val="43" />
                <ind val="32" />
                <ind val="33" />
                <ind val="33" />
                <ind val="44" />
                <ind val="33" />
                <ind val="45" />
                <ind val="34" />
                <ind val="46" />
                <ind val="35" />
                <ind val="47" />
                <ind val="36" />
                <ind val="48" />
                <ind val="37" />
                <ind val="49" />
                <ind val="38" />
                <ind val="50" />
                <ind val="39" />
                <ind val="51" />
                <ind val="40" />
                <ind val="52" />
                <ind val="41" />
                <ind val="53" />
                <ind val="42" />
                <ind val="54" />
                <ind val="43" />
                <ind val="44" />
                <ind val="44" />
                <ind val="55" />
                <ind val="44" />
                <ind val="56" />
                <ind val="45" />
                <ind val="57" />
                <ind val="46" />
                <ind val="58" />
                <ind val="47" />
                <ind val="59" />
                <ind val="48" />
                <ind val="60" />
                <ind val="49" />
                <ind val="61" />
                <ind val="50" />
                <ind val="62" />
                <ind val="51" />
                <ind val="63" />
                <ind val="52" />
                <ind val="64" />
                <ind val="53" />
                <ind val="65" />
                <ind val="54" />
                <ind val="55" />
                <ind val="55" />
                <ind val="66" />
                <ind val="55" />
                <ind val="67" />
                <ind val="56" />
                <ind val="68" />
                <ind val="57" />
                <ind val="69" />
                <ind val="58" />
                <ind val="70" />
                <ind val="59" />
                <ind val="71" />
                <ind val="60" />
                <ind val="72" />
                <ind val="61" />
                <ind val="73" />
                <ind val="62" />
                <ind val="74" />
                <ind val="63" />
                <ind val="75" />
                <ind val="64" />
                <ind val="76" />
                <ind val="65" />
                <ind val="66" />
                <ind val="66" />
                <ind val="77" />
                <ind val="66" />
                <ind val="78" />
                <ind val="67" />
                <ind val="79" />
                <ind val="68" />
                <ind val="80" />
                <ind val="69" />
                <ind val="81" />
                <ind val="70" />
                <ind val="82" />
                <ind val="71" />
                <ind val="83" />
                <ind val="72" />
                <ind val="84" />
                <ind val="73" />
                <ind val="85" />
                <ind val="74" />
                <ind val="86" />
                <ind val="75" />
                <ind val="87" />
                <ind val="76" />
                <ind val="77" />
                <ind val="77" />
                <ind val="88" />
                <ind val="77" />
                <ind val="89" />
                <ind val="78" />
                <ind val="90" />
                <ind val="79" />
                <ind val="91" />
                <ind val="80" />
                <ind val="92" />
                <ind val="81" />
                <ind val="93" />
                <ind val="82" />
                <ind val="94" />
                <ind val="83" />
                <ind val="95" />
                <ind val="84" />
                <ind val="96" />
                <ind val="85" />
                <ind val="97" />
                <ind val="86" />
                <ind val="98" />
                <ind val="87" />
                <ind val="88" />
                <ind val="88" />
                <ind val="99" />
                <ind val="88" />
                <ind val="100" />
                <ind val="89" />
                <ind val="101" />
                <ind val="90" />
                <ind val="102" />
                <ind val="91" />
                <ind val="103" />
                <ind val="92" />
                <ind val="104" />
                <ind val="93" />
                <ind val="105" />
                <ind val="94" />
                <ind val="106" />
                <ind val="95" />
                <ind val="107" />
                <ind val="96" />
                <ind val="108" />
                <ind val="97" />
                <ind val="109" />
                <ind val="98" />
                <ind val="99" />
                <ind val="99" />
                <ind val="110" />
                <ind val="99" />
                <ind val="111" />
                <ind val="100" />
                <ind val="112" />
                <ind val="101" />
                <ind val="113" />
                <ind val="102" />
                <ind val="114" />
                <ind val="103" />
                <ind val="115" />
                <ind val="104" />
                <ind val="116" />
                <ind val="105" />
                <ind val="117" />
                <ind val="106" />
                <ind val="118" />
                <ind val="107" />
                <ind val="119" />
                <ind val="108" />
                <ind val="120" />
                <ind val="109" />
                <ind val="110" />
                <ind val="110" />
                <ind val="110" />
                <ind val="221" />
                <ind val="221" />
                <ind val="217" />
                <ind val="222" />
                <ind val="218" />
                <ind val="223" />
                <ind val="219" />
                <ind val="224" />
                <ind val="220" />
                <ind val="221" />
                <ind val="221" />
                <ind val="225" />
                <ind val="221" />
                <ind val="226" />
                <ind val="222" />
                <ind val="227" />
                <ind val="223" />
                <ind val="228" />
                <ind val="224" />
                <ind val="225" />
                <ind val="225" />
                <ind val="229" />
                <ind val="225" />
                <ind val="230" />
                <ind val="226" />
                <ind val="231" />
                <ind val="227" />
                <ind val="232" />
                <ind val="228" />
                <ind val="229" />
                <ind val="229" />
                <ind val="229" />
                <ind val="301" />
                <ind val="301" />
                <ind val="297" />
                <ind val="302" />
                <ind val="298" />
                <ind val="303" />
                <ind val="299" />
                <ind val="304" />
                <ind val="300" />
                <ind val="301" />
                <ind val="301" />
                <ind val="305" />
                <ind val="301" />
                <ind val="306" />
                <ind val="302" />
                <ind val="307" />
                <ind val="303" />
                <ind val="308" />
                <ind val="304" />
                <ind val="305" />
                <ind val="305" />
                <ind val="309" />
                <ind val="305" />
                <ind val="310" />
                <ind val="306" />
                <ind val="311" />
                <ind val="307" />
                <ind val="312" />
                <ind val="308" />
                <ind val="309" />
                <ind val="309" />
                <ind val="309" />
                <ind val="205" />
                <ind val="205" />
                <ind val="201" />
                <ind val="206" />
                <ind val="202" />
                <ind val="207" />
                <ind val="203" />
                <ind val="208" />
                <ind val="204" />
                <ind val="205" />
                <ind val="205" />
                <ind val="209" />
                <ind val="205" />
                <ind val="210" />
                <ind val="206" />
                <ind val="211" />
                <ind val="207" />
                <ind val="212" />
                <ind val="208" />
                <ind val="209" />
                <ind val="209" />
                <ind val="213" />
                <ind val="209" />
                <ind val="214" />
                <ind val="210" />
                <ind val="215" />
                <ind val="211" />
                <ind val="216" />
                <ind val="212" />
                <ind val="213" />
                <ind val="213" />
                <ind val="213" />
                <ind val="141" />
                <ind val="141" />
                <ind val="137" />
                <ind val="142" />
                <ind val="138" />
                <ind val="143" />
                <ind val="139" />
                <ind val="144" />
                <ind val="140" />
                <ind val="141" />
                <ind val="141" />
                <ind val="145" />
                <ind val="141" />
                <ind val="146" />
                <ind val="142" />
                <ind val="147" />
                <ind val="143" />
                <ind val="148" />
                <ind val="144" />
                <ind val="145" />
                <ind val="145" />
                <ind val="149" />
                <ind val="145" />
                <ind val="150" />
                <ind val="146" />
                <ind val="151" />
                <ind val="147" />
                <ind val="152" />
                <ind val="148" />
                <ind val="149" />
                <ind val="149" />
                <ind val="149" />
                <ind val="285" />
                <ind val="285" />
                <ind val="281" />
                <ind val="286" />
                <ind val="282" />
                <ind val="287" />
                <ind val="283" />
                <ind val="288" />
                <ind val="284" />
                <ind val="285" />
                <ind val="285" />
                <ind val="289" />
                <ind val="285" />
                <ind val="290" />
                <ind val="286" />
                <ind val="291" />
                <ind val="287" />
                <ind val="292" />
                <ind val="288" />
                <ind val="289" />
                <ind val="289" />
                <ind val="293" />
                <ind val="289" />
                <ind val="294" />
                <ind val="290" />
                <ind val="295" />
                <ind val="291" />
                <ind val="296" />
                <ind val="292" />
                <ind val="293" />
                <ind val="293" />
                <ind val="293" />
                <ind val="253" />
                <ind val="253" />
                <ind val="249" />
                <ind val="254" />
                <ind val="250" />
                <ind val="255" />
                <ind val="251" />
                <ind val="256" />
                <ind val="252" />
                <ind val="253" />
                <ind val="253" />
                <ind val="257" />
                <ind val="253" />
                <ind val="258" />
                <ind val="254" />
                <ind val="259" />
                <ind val="255" />
                <ind val="260" />
                <ind val="256" />
                <ind val="257" />
                <ind val="257" />
                <ind val="261" />
                <ind val="257" />
                <ind val="262" />
                <ind val="258" />
                <ind val="263" />
                <ind val="259" />
                <ind val="264" />
                <ind val="260" />
                <ind val="261" />
                <ind val="261" />
                <ind val="261" />
                <ind val="125" />
                <ind val="125" />
                <ind val="121" />
                <ind val="126" />
                <ind val="122" />
                <ind val="127" />
                <ind val="123" />
                <ind val="128" />
                <ind val="124" />
                <ind val="125" />
                <ind val="125" />
                <ind val="129" />
                <ind val="125" />
                <ind val="130" />
                <ind val="126" />
                <ind val="131" />
                <ind val="127" />
                <ind val="132" />
                <ind val="128" />
                <ind val="129" />
                <ind val="129" />
                <ind val="133" />
                <ind val="129" />
                <ind val="134" />
                <ind val="130" />
                <ind val="135" />
                <ind val="131" />
                <ind val="136" />
                <ind val="132" />
                <ind val="133" />
                <ind val="133" />
                <ind val="133" />
                <ind val="157" />
                <ind val="157" />
                <ind val="153" />
                <ind val="158" />
                <ind val="154" />
                <ind val="159" />
                <ind val="155" />
                <ind val="160" />
                <ind val="156" />
                <ind val="157" />
                <ind val="157" />
                <ind val="161" />
                <ind val="157" />
                <ind val="162" />
                <ind val="158" />
                <ind val="163" />
                <ind val="159" />
                <ind val="164" />
                <ind val="160" />
                <ind val="161" />
                <ind val="161" />
                <ind val="165" />
                <ind val="161" />
                <ind val="166" />
                <ind val="162" />
                <ind val="167" />
                <ind val="163" />
                <ind val="168" />
                <ind val="164" />
                <ind val="165" />
                <ind val="165" />
                <ind val="165" />
                <ind val="317" />
                <ind val="317" />
                <ind val="313" />
                <ind val="318" />
                <ind val="314" />
                <ind val="319" />
                <ind val="315" />
                <ind val="320" />
                <ind val="316" />
                <ind val="317" />
                <ind val="317" />
                <ind val="321" />
                <ind val="317" />
                <ind val="322" />
                <ind val="318" />
                <ind val="323" />
                <ind val="319" />
                <ind val="324" />
                <ind val="320" />
                <ind val="321" />
                <ind val="321" />
                <ind val="325" />
                <ind val="321" />
                <ind val="326" />
                <ind val="322" />
                <ind val="327" />
                <ind val="323" />
                <ind val="328" />
                <ind val="324" />
                <ind val="325" />
                <ind val="325" />
                <ind val="325" />
                <ind val="237" />
                <ind val="237" />
                <ind val="233" />
                <ind val="238" />
                <ind val="234" />
                <ind val="239" />
                <ind val="235" />
                <ind val="240" />
                <ind val="236" />
                <ind val="237" />
                <ind val="237" />
                <ind val="241" />
                <ind val="237" />
                <ind val="242" />
                <ind val="238" />
                <ind val="243" />
                <ind val="239" />
                <ind val="244" />
                <ind val="240" />
                <ind val="241" />
                <ind val="241" />
                <ind val="245" />
                <ind val="241" />
                <ind val="246" />
                <ind val="242" />
                <ind val="247" />
                <ind val="243" />
                <ind val="248" />
                <ind val="244" />
                <ind val="245" />
                <ind val="245" />
                <ind val="245" />
                <ind val="173" />
                <ind val="173" />
                <ind val="169" />
                <ind val="174" />
                <ind val="170" />
                <ind val="175" />
                <ind val="171" />
                <ind val="176" />
                <ind val="172" />
                <ind val="173" />
                <ind val="173" />
                <ind val="177" />
                <ind val="173" />
                <ind val="178" />
                <ind val="174" />
                <ind val="179" />
                <ind val="175" />
                <ind val="180" />
                <ind val="176" />
                <ind val="177" />
                <ind val="177" />
                <ind val="181" />
                <ind val="177" />
                <ind val="182" />
                <ind val="178" />
                <ind val="183" />
                <ind val="179" />
                <ind val="184" />
                <ind val="180" />
                <ind val="181" />
                <ind val="181" />
                <ind val="181" />
                <ind val="269" />
                <ind val="269" />
                <ind val="265" />
                <ind val="270" />
                <ind val="266" />
                <ind val="271" />
                <ind val="267" />
                <ind val="272" />
                <ind val="268" />
                <ind val="269" />
                <ind val="269" />
                <ind val="273" />
                <ind val="269" />
                <ind val="274" />
                <ind val="270" />
                <ind val="275" />
                <ind val="271" />
                <ind val="276" />
                <ind val="272" />
                <ind val="273" />
                <ind val="273" />
                <ind val="277" />
                <ind val="273" />
                <ind val="278" />
                <ind val="274" />
                <ind val="279" />
                <ind val="275" />
                <ind val="280" />
                <ind val="276" />
                <ind val="277" />
                <ind val="277" />
                <ind val="277" />
                <ind val="189" />
                <ind val="189" />
                <ind val="185" />
                <ind val="190" />
                <ind val="186" />
                <ind val="191" />
                <ind val="187" />
                <ind val="192" />
                <ind val="188" />
                <ind val="189" />
                <ind val="189" />
                <ind val="193" />
                <ind val="189" />
                <ind val="194" />
                <ind val="190" />
                <ind val="195" />
                <ind val="191" />
                <ind val="196" />
                <ind val="192" />
                <ind val="193" />
                <ind val="193" />
                <ind val="197" />
                <ind val="193" />
                <ind val="198" />
                <ind val="194" />
                <ind val="199" />
                <ind val="195" />
                <ind val="200" />
                <ind val="196" />
                <ind val="197" />
                <ind val="197" />
            </strip>
        </strips>
    </branch>
</root>
